datespan/__init__.py
datespan/date_span.py
datespan/date_span_set.py
datespan/parser/__init__.py
datespan/parser/datespanparser.py
datespan/parser/errors.py
datespan/parser/evaluator.py
datespan/parser/lexer.py
datespan/parser/parser.py
tests/__init__.py
tests/test_class_DateSpan.py
tests/test_class_DateSpanParser.py
tests/test_class_DateSpanSet.py
tests/test_datespan_basics.py
tests/test_datespan_methods.py
tests/test_datespanset.py
tests/test_debugging.py
datespan-0.2.9.dist-info/LICENSE
datespan-0.2.9.dist-info/METADATA
datespan-0.2.9.dist-info/WHEEL
datespan-0.2.9.dist-info/top_level.txt
datespan-0.2.9.dist-info/zip-safe
datespan-0.2.9.dist-info/RECORD
