Metadata-Version: 2.1
Name: datespan
Version: 0.2.9
Summary: Effortless date span parsing and management.
Home-page: https://github.com/Zeutschler/datespan
Author: Thomas Zeutschler
Author-email: cubedpandas@gmail.com
Maintainer-email: Thomas Zeutschler <cubedpandas@gmail.com>
License: MIT License
Project-URL: Homepage, https://github.com/Zeutschler/datespan
Project-URL: Documentation, https://github.com/Zeutschler/datespan
Project-URL: Repository, https://github.com/Zeutschler/datespan.git
Project-URL: Issues, https://github.com/Zeutschler/datespan/issues
Project-URL: Changelog, https://github.com/Zeutschler/datespan/CHANGELOG.md
Project-URL: pypi, https://pypi.org/project/datespan/
Keywords: python,datetime,timespan,pandas,numpy,spark,data analysis,sql,dataframe
Platform: any
Classifier: Intended Audience :: Science/Research
Classifier: Intended Audience :: Developers
Classifier: License :: OSI Approved :: MIT License
Classifier: Development Status :: 3 - Alpha
Classifier: Programming Language :: Python :: 3.9
Classifier: Programming Language :: Python :: 3.10
Classifier: Programming Language :: Python :: 3.11
Classifier: Programming Language :: Python :: 3.12
Classifier: Topic :: Software Development
Classifier: Topic :: Scientific/Engineering
Classifier: Operating System :: Microsoft :: Windows
Classifier: Operating System :: POSIX
Classifier: Operating System :: Unix
Classifier: Operating System :: MacOS
Requires-Python: >= 3.9
License-File: LICENSE
Requires-Dist: python-dateutil
